README.md
setup.py
cloudberry_docker_manager/__init__.py
cloudberry_docker_manager/apply.py
cloudberry_docker_manager/cli.py
cloudberry_docker_manager.egg-info/PKG-INFO
cloudberry_docker_manager.egg-info/SOURCES.txt
cloudberry_docker_manager.egg-info/dependency_links.txt
cloudberry_docker_manager.egg-info/entry_points.txt
cloudberry_docker_manager.egg-info/requires.txt
cloudberry_docker_manager.egg-info/top_level.txt