Metadata-Version: 1.0
Name: cloudberry-docker-manager
Version: 0.1.1
Summary: A docker container manager for Cloudberry
Home-page: https://github.com/innovationgarage/cloudberry-docker-manager
Author: Egil Moeller
Author-email: egil@innovationgarage.no
License: UNKNOWN
Platform: UNKNOWN
